smartllm/__init__.py
smartllm/async_llm.py
smartllm/async_provider_manager.py
smartllm/async_smart_llm.py
smartllm/config.py
smartllm/provider_manager.py
smartllm/smart_llm.py
smartllm/async_providers/__init__.py
smartllm/async_providers/async_anthropic_provider.py
smartllm/async_providers/async_base.py
smartllm/async_providers/async_openai_provider.py
smartllm/async_providers/base.py
smartllm/execution/__init__.py
smartllm/execution/state.py
smartllm/providers/__init__.py
smartllm/providers/anthropic_provider.py
smartllm/providers/base.py
smartllm/providers/openai_provider.py
smartllm/providers/perplexity_provider.py
smartllm-0.0.8.dist-info/METADATA
smartllm-0.0.8.dist-info/WHEEL
smartllm-0.0.8.dist-info/top_level.txt
smartllm-0.0.8.dist-info/RECORD
