Metadata-Version: 2.4
Name: smartllm
Version: 0.0.8
Summary: A unified interface for interacting with multiple Large Language Model providers
Author-email: Arved Klöhn <arved.kloehn@gmail.com>
Project-URL: Homepage, https://github.com/Redundando/smartllm
Keywords: llm,openai,anthropic,perplexity,nlp,ai
Classifier: Programming Language :: Python :: 3
Classifier: Programming Language :: Python :: 3.8
Classifier: Programming Language :: Python :: 3.9
Classifier: Programming Language :: Python :: 3.10
Classifier: Programming Language :: Python :: 3.11
Classifier: License :: OSI Approved :: MIT License
Classifier: Operating System :: OS Independent
Classifier: Intended Audience :: Developers
Classifier: Topic :: Software Development :: Libraries :: Python Modules
Classifier: Topic :: Scientific/Engineering :: Artificial Intelligence
Requires-Python: >=3.8
Requires-Dist: logorator
Requires-Dist: cacherator
Requires-Dist: openai>=1.0.0
Requires-Dist: anthropic>=0.5.0
Requires-Dist: python-slugify
